glpk5_0.cpython-311-x86_64-linux-gnu.so
scikit_glpk-0.5.0.dist-info/RECORD
scikit_glpk-0.5.0.dist-info/METADATA
scikit_glpk-0.5.0.dist-info/top_level.txt
scikit_glpk-0.5.0.dist-info/LICENSE
scikit_glpk-0.5.0.dist-info/WHEEL
glpk/__init__.py
glpk/_utils.py
glpk/_glpk_defines.py
glpk/_fileio.py
glpk/_glpk.py
glpk/tests/__init__.py
glpk/tests/test_examples.py
