Metadata-Version: 1.2
Name: scikit-glpk
Version: 0.5.0
Summary: Python linprog interface for GLPK
Home-page: https://github.com/mckib2/scikit-glpk
Author: Nicholas McKibben
Author-email: nicholas.bgp@gmail.com
License: MIT
Keywords: glpk linprog scikit
Platform: UNKNOWN
Requires-Python: >=3.8
